LICENSE
README.md
pyproject.toml
setup.py
src/pypg_cdc.egg-info/PKG-INFO
src/pypg_cdc.egg-info/SOURCES.txt
src/pypg_cdc.egg-info/dependency_links.txt
src/pypg_cdc.egg-info/requires.txt
src/pypg_cdc.egg-info/top_level.txt
src/pypgoutput/__init__.py
src/pypgoutput/decoders.py
src/pypgoutput/reader.py
src/pypgoutput/utils.py