Metadata-Version: 2.1
Name: pypg-cdc
Version: 0.0.1
Summary: PostgreSQL CDC library using pgoutput and python
Home-page: https://github.com/sshd123/pypgoutput
Author: sjy
Author-email: 
Classifier: Programming Language :: Python :: 3
Classifier: Programming Language :: Python :: 3.8
Classifier: Programming Language :: Python :: 3.9
Classifier: Programming Language :: Python :: 3.10
Classifier: Programming Language :: Python :: 3.11
Classifier: License :: OSI Approved :: MIT License
Classifier: Operating System :: OS Independent
Requires-Python: >=3.8
License-File: LICENSE
